gdshoplib/.DS_Store
gdshoplib/__init__.py
gdshoplib/__main__.py
gdshoplib/activities/notion.py
gdshoplib/apps/__init__.py
gdshoplib/apps/crm/cart.py
gdshoplib/apps/crm/dialog.py
gdshoplib/apps/crm/on_request.py
gdshoplib/apps/crm/orders.py
gdshoplib/apps/crm/stats.py
gdshoplib/apps/delivery/delivery.py
gdshoplib/apps/finance/__init__.py
gdshoplib/apps/finance/storage.py
gdshoplib/apps/marketing/__init__.py
gdshoplib/apps/payments/payments.py
gdshoplib/apps/platforms/README.md
gdshoplib/apps/platforms/__init__.py
gdshoplib/apps/platforms/avito.py
gdshoplib/apps/platforms/base.py
gdshoplib/apps/platforms/instagram.py
gdshoplib/apps/platforms/ok.py
gdshoplib/apps/platforms/sm.py
gdshoplib/apps/platforms/tg.py
gdshoplib/apps/platforms/ula.py
gdshoplib/apps/platforms/vk.py
gdshoplib/apps/platforms/web.py
gdshoplib/apps/platforms/yam.py
gdshoplib/apps/platforms/yamb.py
gdshoplib/apps/products/README.md
gdshoplib/apps/products/__init__.py
gdshoplib/apps/products/description.py
gdshoplib/apps/products/media.py
gdshoplib/apps/products/price.py
gdshoplib/apps/products/product.py
gdshoplib/apps/uploader/uploader.py
gdshoplib/cli/application.py
gdshoplib/cli/crm/application.py
gdshoplib/cli/crm/order.py
gdshoplib/cli/crm/stats.py
gdshoplib/cli/finance/application.py
gdshoplib/cli/finance/store.py
gdshoplib/cli/product/application.py
gdshoplib/cli/product/barcode_cli.py
gdshoplib/cli/product/cache.py
gdshoplib/cli/product/controle.py
gdshoplib/cli/product/description.py
gdshoplib/cli/product/feed.py
gdshoplib/cli/product/media.py
gdshoplib/cli/product/price.py
gdshoplib/cli/service/application.py
gdshoplib/cli/service/avito.py
gdshoplib/cli/service/vk.py
gdshoplib/cli/stock/application.py
gdshoplib/cli/stock/cart.py
gdshoplib/cli/temporal/application.py
gdshoplib/core/ecosystem.py
gdshoplib/core/settings.py
gdshoplib/packages/__init__.py
gdshoplib/packages/barcode_pack.py
gdshoplib/packages/cache.py
gdshoplib/packages/feed.py
gdshoplib/packages/lang.py
gdshoplib-2.5.2.dist-info/METADATA
gdshoplib-2.5.2.dist-info/WHEEL
gdshoplib-2.5.2.dist-info/entry_points.txt
gdshoplib-2.5.2.dist-info/RECORD
